{
  "champions-tunic": {
    "regions": [
      "Kakariko Village (Dueling Peaks)"
    ],
    "where": "Given by Impa during the main quest 'Captured Memories'."
  },
  "sand-boots": {
    "regions": [
      "Gerudo Desert",
      "Gerudo Town / Kara Kara Bazaar"
    ],
    "where": "Earned via Bozai side quests (then can be repurchased from Granté if sold)."
  },
  "snow-boots": {
    "regions": [
      "Gerudo Desert",
      "Gerudo Town / Kara Kara Bazaar"
    ],
    "where": "Earned via Bozai side quests (then can be repurchased from Granté if sold)."
  },
  "ancient-helm": {
    "regions": [
      "Akkala (Akkala Ancient Tech Lab)"
    ],
    "where": "Purchase from the Akkala Ancient Tech Lab after 'Robbie's Research' (requires Ancient materials)."
  },
  "ancient-cuirass": {
    "regions": [
      "Akkala (Akkala Ancient Tech Lab)"
    ],
    "where": "Purchase from the Akkala Ancient Tech Lab after 'Robbie's Research' (requires Ancient materials)."
  },
  "ancient-greaves": {
    "regions": [
      "Akkala (Akkala Ancient Tech Lab)"
    ],
    "where": "Purchase from the Akkala Ancient Tech Lab after 'Robbie's Research' (requires Ancient materials)."
  },
  "barbarian-helm": {
    "regions": [
      "Labyrinths (Hebra / Akkala / Gerudo Highlands)"
    ],
    "where": "Found in chests inside the three Lomei Labyrinth shrine-quests (one piece per labyrinth)."
  },
  "barbarian-armor": {
    "regions": [
      "Labyrinths (Hebra / Akkala / Gerudo Highlands)"
    ],
    "where": "Found in chests inside the three Lomei Labyrinth shrine-quests (one piece per labyrinth)."
  },
  "barbarian-leg-wraps": {
    "regions": [
      "Labyrinths (Hebra / Akkala / Gerudo Highlands)"
    ],
    "where": "Found in chests inside the three Lomei Labyrinth shrine-quests (one piece per labyrinth)."
  },
  "climbers-bandanna": {
    "regions": [
      "Dueling Peaks"
    ],
    "where": "Chest in Ree Dahee Shrine (Dueling Peaks)."
  },
  "climbing-gear": {
    "regions": [
      "Hateno Bay / Tenoko Island"
    ],
    "where": "Chest in Chaas Qeta Shrine (Tenoko Island, off Hateno Bay)."
  },
  "climbing-boots": {
    "regions": [
      "Lanayru Range (Mount Lanayru)"
    ],
    "where": "Chest in Tahno O'ah Shrine (Mount Lanayru)."
  },
  "desert-voe-headband": {
    "regions": [
      "Gerudo Desert (Gerudo Town)"
    ],
    "where": "Sold by the Gerudo Secret Club in Gerudo Town."
  },
  "desert-voe-spaulder": {
    "regions": [
      "Gerudo Desert (Gerudo Town)"
    ],
    "where": "Sold by the Gerudo Secret Club in Gerudo Town."
  },
  "desert-voe-trousers": {
    "regions": [
      "Gerudo Desert (Gerudo Town)"
    ],
    "where": "Sold by the Gerudo Secret Club in Gerudo Town."
  },
  "flamebreaker-helm": {
    "regions": [
      "Eldin (Goron City)"
    ],
    "where": "Sold in Goron City; the torso piece is also given during 'Fireproof Lizard Roundup'."
  },
  "flamebreaker-armor": {
    "regions": [
      "Eldin (Goron City)"
    ],
    "where": "Sold in Goron City; the torso piece is also given during 'Fireproof Lizard Roundup'."
  },
  "flamebreaker-boots": {
    "regions": [
      "Eldin (Goron City)"
    ],
    "where": "Sold in Goron City; the torso piece is also given during 'Fireproof Lizard Roundup'."
  },
  "hylian-hood": {
    "regions": [
      "Hateno Village"
    ],
    "where": "Sold in Hateno Village's armor shop."
  },
  "hylian-tunic": {
    "regions": [
      "Hateno Village"
    ],
    "where": "Sold in Hateno Village's armor shop."
  },
  "hylian-trousers": {
    "regions": [
      "Hateno Village"
    ],
    "where": "Sold in Hateno Village's armor shop."
  },
  "radiant-mask": {
    "regions": [
      "Gerudo Desert (Gerudo Town)"
    ],
    "where": "Sold in Gerudo Town at the Clothing Boutique (Radiant Set)."
  },
  "radiant-shirt": {
    "regions": [
      "Gerudo Desert (Gerudo Town)"
    ],
    "where": "Sold in Gerudo Town at the Clothing Boutique (Radiant Set)."
  },
  "radiant-tights": {
    "regions": [
      "Gerudo Desert (Gerudo Town)"
    ],
    "where": "Sold in Gerudo Town at the Clothing Boutique (Radiant Set)."
  },
  "stealth-mask": {
    "regions": [
      "Kakariko Village"
    ],
    "where": "Sold in Kakariko Village at Enchanted (Stealth Set)."
  },
  "stealth-chest-guard": {
    "regions": [
      "Kakariko Village"
    ],
    "where": "Sold in Kakariko Village at Enchanted (Stealth Set)."
  },
  "stealth-tights": {
    "regions": [
      "Kakariko Village"
    ],
    "where": "Sold in Kakariko Village at Enchanted (Stealth Set)."
  },
  "snowquill-headdress": {
    "regions": [
      "Hebra (Rito Village)"
    ],
    "where": "Sold in Rito Village's armor shop (Snowquill Set)."
  },
  "snowquill-tunic": {
    "regions": [
      "Hebra (Rito Village)"
    ],
    "where": "Sold in Rito Village's armor shop (Snowquill Set)."
  },
  "snowquill-trousers": {
    "regions": [
      "Hebra (Rito Village)"
    ],
    "where": "Sold in Rito Village's armor shop (Snowquill Set)."
  },
  "soldiers-helm": {
    "regions": [
      "Hateno Village"
    ],
    "where": "Sold in Hateno Village's armor shop (Soldier's Set)."
  },
  "soldiers-armor": {
    "regions": [
      "Hateno Village"
    ],
    "where": "Sold in Hateno Village's armor shop (Soldier's Set)."
  },
  "soldiers-greaves": {
    "regions": [
      "Hateno Village"
    ],
    "where": "Sold in Hateno Village's armor shop (Soldier's Set)."
  },
  "rubber-helm": {
    "regions": [
      "Faron / Thunderstorm regions"
    ],
    "where": "Found in treasure chests in specific shrines/quests tied to thunderstorms (Rubber Set)."
  },
  "rubber-armor": {
    "regions": [
      "Faron / Thunderstorm regions"
    ],
    "where": "Found in treasure chests in specific shrines/quests tied to thunderstorms (Rubber Set)."
  },
  "rubber-tights": {
    "regions": [
      "Faron / Thunderstorm regions"
    ],
    "where": "Found in treasure chests in specific shrines/quests tied to thunderstorms (Rubber Set)."
  },
  "zora-helm": {
    "regions": [
      "Lanayru (Zora's Domain)"
    ],
    "where": "Obtained through Zora's Domain story/side content (Zora Set)."
  },
  "zora-armor": {
    "regions": [
      "Lanayru (Zora's Domain)"
    ],
    "where": "Obtained through Zora's Domain story/side content (Zora Set)."
  },
  "zora-greaves": {
    "regions": [
      "Lanayru (Zora's Domain)"
    ],
    "where": "Obtained through Zora's Domain story/side content (Zora Set)."
  },
  "cap-of-the-wild": {
    "regions": [
      "Forgotten Temple (Central/North Hyrule)"
    ],
    "where": "Reward for completing all shrines: found in chests in the Forgotten Temple (Wild Set)."
  },
  "tunic-of-the-wild": {
    "regions": [
      "Forgotten Temple (Central/North Hyrule)"
    ],
    "where": "Reward for completing all shrines: found in chests in the Forgotten Temple (Wild Set)."
  },
  "trousers-of-the-wild": {
    "regions": [
      "Forgotten Temple (Central/North Hyrule)"
    ],
    "where": "Reward for completing all shrines: found in chests in the Forgotten Temple (Wild Set)."
  },
  "amber-earrings": {
    "regions": [
      "Gerudo Desert (Gerudo Town)"
    ],
    "where": "Sold at the jewelry shop in Gerudo Town (Starlight Memories)."
  },
  "diamond-circlet": {
    "regions": [
      "Gerudo Desert (Gerudo Town)"
    ],
    "where": "Sold at the jewelry shop in Gerudo Town (Starlight Memories)."
  },
  "opal-earrings": {
    "regions": [
      "Gerudo Desert (Gerudo Town)"
    ],
    "where": "Sold at the jewelry shop in Gerudo Town (Starlight Memories)."
  },
  "ruby-circlet": {
    "regions": [
      "Gerudo Desert (Gerudo Town)"
    ],
    "where": "Sold at the jewelry shop in Gerudo Town (Starlight Memories)."
  },
  "sapphire-circlet": {
    "regions": [
      "Gerudo Desert (Gerudo Town)"
    ],
    "where": "Sold at the jewelry shop in Gerudo Town (Starlight Memories)."
  },
  "topaz-earrings": {
    "regions": [
      "Gerudo Desert (Gerudo Town)"
    ],
    "where": "Sold at the jewelry shop in Gerudo Town (Starlight Memories)."
  },
  "fierce-deity-mask": {
    "regions": [
      "Amiibo"
    ],
    "where": "Exclusive to Amiibo treasure chest drops (scan the matching Zelda-series amiibo)."
  },
  "fierce-deity-armor": {
    "regions": [
      "Amiibo"
    ],
    "where": "Exclusive to Amiibo treasure chest drops (scan the matching Zelda-series amiibo)."
  },
  "fierce-deity-boots": {
    "regions": [
      "Amiibo"
    ],
    "where": "Exclusive to Amiibo treasure chest drops (scan the matching Zelda-series amiibo)."
  },
  "cap-of-the-hero": {
    "regions": [
      "Amiibo"
    ],
    "where": "Exclusive to Amiibo treasure chest drops (scan the matching Zelda-series amiibo)."
  },
  "tunic-of-the-hero": {
    "regions": [
      "Amiibo"
    ],
    "where": "Exclusive to Amiibo treasure chest drops (scan the matching Zelda-series amiibo)."
  },
  "trousers-of-the-hero": {
    "regions": [
      "Amiibo"
    ],
    "where": "Exclusive to Amiibo treasure chest drops (scan the matching Zelda-series amiibo)."
  },
  "cap-of-the-sky": {
    "regions": [
      "Amiibo"
    ],
    "where": "Exclusive to Amiibo treasure chest drops (scan the matching Zelda-series amiibo)."
  },
  "tunic-of-the-sky": {
    "regions": [
      "Amiibo"
    ],
    "where": "Exclusive to Amiibo treasure chest drops (scan the matching Zelda-series amiibo)."
  },
  "trousers-of-the-sky": {
    "regions": [
      "Amiibo"
    ],
    "where": "Exclusive to Amiibo treasure chest drops (scan the matching Zelda-series amiibo)."
  },
  "cap-of-time": {
    "regions": [
      "Amiibo"
    ],
    "where": "Exclusive to Amiibo treasure chest drops (scan the matching Zelda-series amiibo)."
  },
  "tunic-of-time": {
    "regions": [
      "Amiibo"
    ],
    "where": "Exclusive to Amiibo treasure chest drops (scan the matching Zelda-series amiibo)."
  },
  "trousers-of-time": {
    "regions": [
      "Amiibo"
    ],
    "where": "Exclusive to Amiibo treasure chest drops (scan the matching Zelda-series amiibo)."
  },
  "cap-of-twilight": {
    "regions": [
      "Amiibo"
    ],
    "where": "Exclusive to Amiibo treasure chest drops (scan the matching Zelda-series amiibo)."
  },
  "tunic-of-twilight": {
    "regions": [
      "Amiibo"
    ],
    "where": "Exclusive to Amiibo treasure chest drops (scan the matching Zelda-series amiibo)."
  },
  "trousers-of-twilight": {
    "regions": [
      "Amiibo"
    ],
    "where": "Exclusive to Amiibo treasure chest drops (scan the matching Zelda-series amiibo)."
  },
  "cap-of-the-wind": {
    "regions": [
      "Amiibo"
    ],
    "where": "Exclusive to Amiibo treasure chest drops (scan the matching Zelda-series amiibo)."
  },
  "tunic-of-the-wind": {
    "regions": [
      "Amiibo"
    ],
    "where": "Exclusive to Amiibo treasure chest drops (scan the matching Zelda-series amiibo)."
  },
  "trousers-of-the-wind": {
    "regions": [
      "Amiibo"
    ],
    "where": "Exclusive to Amiibo treasure chest drops (scan the matching Zelda-series amiibo)."
  },
  "sheiks-mask": {
    "regions": [
      "DLC (EX Treasure)"
    ],
    "where": "DLC chest (EX Treasure): Sheik's Mask — follow 'EX Treasure: Ancient Mask' quest hint."
  },
  "vah-medoh-divine-helm": {
    "regions": [
      "DLC (EX Treasure)"
    ],
    "where": "DLC chest (EX Treasure): Divine Beast Helm — follow the corresponding EX treasure quest."
  },
  "vah-naboris-divine-helm": {
    "regions": [
      "DLC (EX Treasure)"
    ],
    "where": "DLC chest (EX Treasure): Divine Beast Helm — follow the corresponding EX treasure quest."
  },
  "vah-rudania-divine-helm": {
    "regions": [
      "DLC (EX Treasure)"
    ],
    "where": "DLC chest (EX Treasure): Divine Beast Helm — follow the corresponding EX treasure quest."
  },
  "vah-ruta-divine-helm": {
    "regions": [
      "DLC (EX Treasure)"
    ],
    "where": "DLC chest (EX Treasure): Divine Beast Helm — follow the corresponding EX treasure quest."
  }
}